flask_devpost_oauth/__init__.py
flask_devpost_oauth-1.0.0.dist-info/LICENSE
flask_devpost_oauth-1.0.0.dist-info/METADATA
flask_devpost_oauth-1.0.0.dist-info/WHEEL
flask_devpost_oauth-1.0.0.dist-info/top_level.txt
flask_devpost_oauth-1.0.0.dist-info/RECORD
