Metadata-Version: 2.1
Name: flask-devpost-oauth
Version: 1.0.0
Summary: Brings DevPost OAuth to Flask.
Home-page: https://replit.com/@EpicCodeWizard/Flask-Devpost-OAuth-Extension
Author: EpicCodeWizard
Author-email: epiccodewizard@gmail.com
License: UNKNOWN
Platform: UNKNOWN
Classifier: Programming Language :: Python :: 3
Classifier: License :: OSI Approved :: MIT License
Classifier: Operating System :: OS Independent
Requires-Dist: Flask (==2.0.2)
Requires-Dist: gunicorn (==20.1.0)
Requires-Dist: eventlet (==0.33.0)
Requires-Dist: gevent-websocket
Requires-Dist: python-socketio (==4.6.0)
Requires-Dist: python-engineio (==3.13.2)
Requires-Dist: Flask-SocketIO (==4.3.1)
